iam_python_sdk/__init__.py
iam_python_sdk/async_client.py
iam_python_sdk/bloom.py
iam_python_sdk/cache.py
iam_python_sdk/cli.py
iam_python_sdk/client.py
iam_python_sdk/config.py
iam_python_sdk/errors.py
iam_python_sdk/fastapi.py
iam_python_sdk/flask.py
iam_python_sdk/http_errors.py
iam_python_sdk/log.py
iam_python_sdk/models.py
iam_python_sdk/task.py
iam_python_sdk/utils.py
iam_python_sdk-1.4.3.dist-info/AUTHORS.rst
iam_python_sdk-1.4.3.dist-info/LICENSE
iam_python_sdk-1.4.3.dist-info/METADATA
iam_python_sdk-1.4.3.dist-info/WHEEL
iam_python_sdk-1.4.3.dist-info/entry_points.txt
iam_python_sdk-1.4.3.dist-info/top_level.txt
iam_python_sdk-1.4.3.dist-info/RECORD
