Metadata-Version: 2.1
Name: iam-python-sdk
Version: 1.4.3
Summary: AccelByte IAM Python SDK
Home-page: https://accelbyte.github.io/iam-python-sdk
Author: Analytics AccelByte
Author-email: justice-analytics-team@accelbyte.net
License: Apache Software License 2.0
Keywords: iam_python_sdk,accelbyte,iam
Classifier: Development Status :: 5 - Production/Stable
Classifier: Intended Audience :: Developers
Classifier: License :: OSI Approved :: Apache Software License
Classifier: Natural Language :: English
Classifier: Programming Language :: Python :: 3
Classifier: Programming Language :: Python :: 3.6
Classifier: Programming Language :: Python :: 3.7
Classifier: Programming Language :: Python :: 3.8
Classifier: Programming Language :: Python :: 3.9
Requires-Python: >=3.6
License-File: LICENSE
License-File: AUTHORS.rst
Requires-Dist: Click<8.1.0,>=7.1.2
Requires-Dist: backoff==1.11.1
Requires-Dist: httpx==0.22.0
Requires-Dist: httpcore==0.14.5
Requires-Dist: pyjwt[crypto]==2.4.0
Requires-Dist: crontab==0.23.0
Requires-Dist: bitarray==2.3.4
Requires-Dist: mmh3==3.0.0
Provides-Extra: fastapi
Requires-Dist: fastapi<=0.90.1; extra == "fastapi"
Provides-Extra: flask
Requires-Dist: Flask<3.0,>=1.0; extra == "flask"
